LICENSE
dropland/__init__.py
dropland/app/__init__.py
dropland/app/application.py
dropland/app/base.py
dropland/app/module.py
dropland/app/service.py
dropland/core/__init__.py
dropland/core/loaders/__init__.py
dropland/core/loaders/backend.py
dropland/core/loaders/module.py
dropland/core/metaclass.py
dropland/data/__init__.py
dropland/data/cache/__init__.py
dropland/data/cache/base.py
dropland/data/cache/method.py
dropland/data/context.py
dropland/data/entities.py
dropland/data/models/__init__.py
dropland/data/models/base.py
dropland/data/models/fields.py
dropland/data/models/local_cache.py
dropland/data/models/model.py
dropland/data/models/relationship.py
dropland/data/models/serializable.py
dropland/data/repositories.py
dropland/data/serializers/__init__.py
dropland/data/serializers/pickle.py
dropland/engines/__init__.py
dropland/engines/base.py
dropland/engines/databases/__init__.py
dropland/engines/databases/containers.py
dropland/engines/databases/engine.py
dropland/engines/elasticsearch/__init__.py
dropland/engines/elasticsearch/containers.py
dropland/engines/elasticsearch/engine.py
dropland/engines/elasticsearch/settings.py
dropland/engines/module.py
dropland/engines/redis/__init__.py
dropland/engines/redis/cache.py
dropland/engines/redis/containers.py
dropland/engines/redis/engine.py
dropland/engines/redis/model.py
dropland/engines/redis/repositories.py
dropland/engines/redis/settings.py
dropland/engines/rmq/__init__.py
dropland/engines/rmq/client.py
dropland/engines/rmq/containers.py
dropland/engines/rmq/engine.py
dropland/engines/rmq/server.py
dropland/engines/rmq/settings.py
dropland/engines/scheduler/__init__.py
dropland/engines/scheduler/application.py
dropland/engines/scheduler/containers.py
dropland/engines/scheduler/engine.py
dropland/engines/scheduler/local.py
dropland/engines/scheduler/remote.py
dropland/engines/scheduler/settings.py
dropland/engines/sql.py
dropland/engines/sqla/__init__.py
dropland/engines/sqla/containers.py
dropland-0.9.3.dist-info/LICENSE
dropland-0.9.3.dist-info/WHEEL
dropland-0.9.3.dist-info/METADATA
dropland-0.9.3.dist-info/RECORD
